{
  "image": "/home/albert/code/CV/auxiliary/images/cod10k_0012.png",
  "width": 1024,
  "height": 680,
  "rows": 9,
  "cols": 9,
  "row_boxes": [
    [
      0,
      0,
      -1,
      75
    ],
    [
      0,
      76,
      -1,
      150
    ],
    [
      0,
      151,
      -1,
      226
    ],
    [
      0,
      227,
      -1,
      301
    ],
    [
      0,
      302,
      -1,
      377
    ],
    [
      0,
      378,
      -1,
      452
    ],
    [
      0,
      453,
      -1,
      528
    ],
    [
      0,
      529,
      -1,
      603
    ],
    [
      0,
      604,
      -1,
      679
    ]
  ],
  "col_boxes": [
    [
      0,
      0,
      113,
      -1
    ],
    [
      114,
      0,
      227,
      -1
    ],
    [
      228,
      0,
      340,
      -1
    ],
    [
      341,
      0,
      454,
      -1
    ],
    [
      455,
      0,
      568,
      -1
    ],
    [
      569,
      0,
      682,
      -1
    ],
    [
      683,
      0,
      795,
      -1
    ],
    [
      796,
      0,
      909,
      -1
    ],
    [
      910,
      0,
      1023,
      -1
    ]
  ],
  "note": "行号/列号均为 1 开始计数；与图片上的编号一致。"
}